ipyweb/__init__.py
ipyweb/app.py
ipyweb/appRunner.py
ipyweb/cache.py
ipyweb/cli.py
ipyweb/command.py
ipyweb/config.py
ipyweb/controller.py
ipyweb/db.py
ipyweb/event.py
ipyweb/gui.py
ipyweb/ipyweb.py
ipyweb/jsonFile.py
ipyweb/logger.py
ipyweb/module.py
ipyweb/preload.py
ipyweb/process.py
ipyweb/service.py
ipyweb/singleton.py
ipyweb/thread.py
ipyweb/utils.py
ipyweb/addons/loadingGui.py
ipyweb/builds/builder.py
ipyweb/builds/hooks/hook-cefpython3.py
ipyweb/builds/hooks/hook-ipyweb.py
ipyweb/commands/ipywebBaser.py
ipyweb/commands/ipywebBuilder.py
ipyweb/commands/ipywebRunner.py
ipyweb/configs/app.py
ipyweb/configs/build.py
ipyweb/configs/cache.py
ipyweb/configs/database.py
ipyweb/configs/jsonFile.py
ipyweb/configs/logger.py
ipyweb/configs/windows.py
ipyweb/contracts/ipywebAddon.py
ipyweb/contracts/ipywebController.py
ipyweb/contracts/ipywebException.py
ipyweb/contracts/ipywebHttpController.py
ipyweb/contracts/ipywebModel.py
ipyweb/contracts/ipywebPreload.py
ipyweb/contracts/ipywebQueue.py
ipyweb/contracts/ipywebRunner.py
ipyweb/controllers/ipyweb.py
ipyweb/events/listener/windows.py
ipyweb/events/register/windows.py
ipyweb/guis/BottleServer.py
ipyweb/guis/FlaskServer.py
ipyweb/guis/IpywebServer.py
ipyweb/guis/LocalServer.py
ipyweb/guis/RemoteServer.py
ipyweb/preloads/block/controllerPreload.py
ipyweb/preloads/block/guiPreload.py
ipyweb/preloads/block/processPreload.py
ipyweb/preloads/process/examplePreload.py
ipyweb/preloads/thread/crontabPreload.py
ipyweb/preloads/thread/queuePreload.py
ipyweb/preloads/thread/socketPreload.py
ipyweb/preloads/thread/timerPreload.py
ipyweb/pywebview/windows.py
ipyweb/services/crontab.py
ipyweb/services/queue.py
ipyweb/services/socketClient.py
ipyweb/services/socketServer.py
ipyweb/services/timer.py
ipyweb/windowEvents/main.py
ipyweb-1.1.1.dist-info/LICENSE
ipyweb-1.1.1.dist-info/METADATA
ipyweb-1.1.1.dist-info/WHEEL
ipyweb-1.1.1.dist-info/entry_points.txt
ipyweb-1.1.1.dist-info/top_level.txt
ipyweb-1.1.1.dist-info/RECORD
