Metadata-Version: 2.1
Name: ipyweb
Version: 1.1.1
Summary: A business framework for launching multiple services
Author-email: sqwindows <sqwindows@qq.com>
License: BSD 3-Clause License
Keywords: gui,webkit,html,web
Requires-Python: >=3.8
License-File: LICENSE
Requires-Dist: ipywebview
Requires-Dist: blinker
Requires-Dist: click
